<?xml version="1.0" encoding="utf-8" standalone="no"?>
<!DOCTYPE properties SYSTEM "http://java.sun.com/dtd/properties.dtd">
<properties version="1.0">
	<comment>
		-- DataExplorer Messwert Mapping Datei --
		diese Datei enthaelt Mappings von Messwerten bei denen die Skala synchronisiert werden soll
		fehlende Mappings einfach ergaenzen, bitte informieren Sie den Entwickler
	</comment>
	<entry key="Rx_UBatt_1">Rx_UBatt_0</entry>

	<entry key="RXSub1_UBatt_1">RXSub1_UBatt_0</entry>
	<entry key="RXSub2_UBatt_0">RXSub1_UBatt_0</entry>
	<entry key="RXSub2_UBatt_1">RXSub1_UBatt_0</entry>

	<entry key="Tx_StatusWord">Rx_StatusWord</entry>
	<entry key="Tx_HKStatusWord">Rx_StatusWord</entry>
	<entry key="RXSub1_StatusWord">Rx_StatusWord</entry>
	<entry key="RXSub2_StatusWord">Rx_StatusWord</entry>
	<entry key="RXSub1_StatusByte">Rx_StatusWord</entry>
	<entry key="RXSub2_StatusByte">Rx_StatusWord</entry>

	<entry key="Tx_PowerSupply_Status Cell1">Tx_PowerSupply_Status Main</entry>
	<entry key="Tx_PowerSupply_Status Cell2">Tx_PowerSupply_Status Main</entry>
	<entry key="Tx_PowerSupply_Status Cell3">Tx_PowerSupply_Status Main</entry>
	<entry key="Tx_PowerSupply_Status Cell4">Tx_PowerSupply_Status Main</entry>

	<entry key="Tx_PowerSupply_Voltage Cell1">Tx_PowerSupply_Voltage Main</entry>
	<entry key="Tx_PowerSupply_Voltage Cell2">Tx_PowerSupply_Voltage Main</entry>
	<entry key="Tx_PowerSupply_Voltage Cell3">Tx_PowerSupply_Voltage Main</entry>
	<entry key="Tx_PowerSupply_Voltage Cell4">Tx_PowerSupply_Voltage Main</entry>

	<entry key="Tx_PowerSupply_InputVoltage Cell1">Tx_PowerSupply_InputVoltage Main</entry>
	<entry key="Tx_PowerSupply_InputVoltage Cell2">Tx_PowerSupply_InputVoltage Main</entry>
	<entry key="Tx_PowerSupply_InputVoltage Cell3">Tx_PowerSupply_InputVoltage Main</entry>
	<entry key="Tx_PowerSupply_InputVoltage Cell4">Tx_PowerSupply_InputVoltage Main</entry>
		
	<entry key="Tx_PowerSupply_Current Cell1">Tx_PowerSupply_Current Main</entry>
	<entry key="Tx_PowerSupply_Current Cell2">Tx_PowerSupply_Current Main</entry>
	<entry key="Tx_PowerSupply_Current Cell3">Tx_PowerSupply_Current Main</entry>
	<entry key="Tx_PowerSupply_Current Cell4">Tx_PowerSupply_Current Main</entry>
		
	<entry key="Tx_PowerSupply_InputCurrent Cell1">Tx_PowerSupply_InputCurrent Main</entry>
	<entry key="Tx_PowerSupply_InputCurrent Cell2">Tx_PowerSupply_InputCurrent Main</entry>
	<entry key="Tx_PowerSupply_InputCurrent Cell3">Tx_PowerSupply_InputCurrent Main</entry>
	<entry key="Tx_PowerSupply_InputCurrent Cell4">Tx_PowerSupply_InputCurrent Main</entry>
		
	<entry key="Tx_PowerSupply_Temperature Cell1">Tx_PowerSupply_InputTemperature Main</entry>
	<entry key="Tx_PowerSupply_Temperature Cell2">Tx_PowerSupply_InputTemperature Main</entry>
	<entry key="Tx_PowerSupply_Temperature Cell3">Tx_PowerSupply_InputTemperature Main</entry>
	<entry key="Tx_PowerSupply_Temperature Cell4">Tx_PowerSupply_InputTemperature Main</entry>
		
	<entry key="Tx_PowerSupply_Capacity Cell2">Tx_PowerSupply_Capacity Cell1</entry>
	<entry key="Tx_PowerSupply_Capacity Cell3">Tx_PowerSupply_Capacity Cell1</entry>
	<entry key="Tx_PowerSupply_Capacity Cell4">Tx_PowerSupply_Capacity Cell1</entry>
		
	<entry key="RXSub1_Temperature">Rx_Temperature</entry>

	<entry key="Rx_RSSI_1">Rx_RSSI_0</entry>
	<entry key="Tx_RSSI_0">Rx_RSSI_0</entry>
	<entry key="Tx_RSSI_1">Rx_RSSI_0</entry>
	
	<entry key="Rx_LQI_1">Rx_LQI_0</entry>
	<entry key="Tx_LQI_0">Rx_LQI_0</entry>
	<entry key="Tx_LQI_1">Rx_LQI_0</entry>

	<entry key="RXSub2_Temperature">Rx_Temperature</entry>
	
	<entry key="RXSub1_RSSI_1">RXSub1_RSSI_0</entry>
	<entry key="RXSub2_RSSI_0">RXSub1_RSSI_0</entry>
	<entry key="RXSub2_RSSI_1">RXSub1_RSSI_0</entry>

	<entry key="RXSub1_LQI_1">RXSub1_LQI_0</entry>
	<entry key="RXSub2_LQI_0">RXSub1_LQI_0</entry>
	<entry key="RXSub2_LQI_1">RXSub1_LQI_0</entry>


	<entry key="Tx_Control__2">Tx_Control__1</entry>
	<entry key="Tx_Control__3">Tx_Control__1</entry>
	<entry key="Tx_Control__4">Tx_Control__1</entry>
	<entry key="Tx_Control__5">Tx_Control__1</entry>
	<entry key="Tx_Control__6">Tx_Control__1</entry>
	<entry key="Tx_Control__7">Tx_Control__1</entry>
	<entry key="Tx_Control__8">Tx_Control__1</entry>
	<entry key="Tx_Control__9">Tx_Control__1</entry>
	<entry key="Tx_Control__10">Tx_Control__1</entry>
	<entry key="Tx_Control__11">Tx_Control__1</entry>
	<entry key="Tx_Control__12">Tx_Control__1</entry>
	<entry key="Tx_Control__13">Tx_Control__1</entry>
	<entry key="Tx_Control__14">Tx_Control__1</entry>
	<entry key="Tx_Control__15">Tx_Control__1</entry>
	<entry key="Tx_Control__16">Tx_Control__1</entry>
	<entry key="Tx_Control__17">Tx_Control__1</entry>
	<entry key="Tx_Control__18">Tx_Control__1</entry>
	<entry key="Tx_Control__19">Tx_Control__1</entry>
	<entry key="Tx_Control__20">Tx_Control__1</entry>
	<entry key="Tx_Control__21">Tx_Control__1</entry>
	<entry key="Tx_Control__22">Tx_Control__1</entry>
	<entry key="Tx_Control__23">Tx_Control__1</entry>
	<entry key="Tx_Control__24">Tx_Control__1</entry>
	<entry key="Tx_Control__25">Tx_Control__1</entry>
	<entry key="Tx_Control__26">Tx_Control__1</entry>
	<entry key="Tx_Control__27">Tx_Control__1</entry>
	<entry key="Tx_Control__28">Tx_Control__1</entry>
	<entry key="Tx_Control__29">Tx_Control__1</entry>
	<entry key="Tx_Control__30">Tx_Control__1</entry>
	<entry key="Tx_Control__31">Tx_Control__1</entry>
	<entry key="Tx_Control__32">Tx_Control__1</entry>
	<entry key="Tx_Control__33">Tx_Control__1</entry>
	<entry key="Tx_Control__34">Tx_Control__1</entry>
	<entry key="Tx_Control__35">Tx_Control__1</entry>
	<entry key="Tx_Control__36">Tx_Control__1</entry>
	<entry key="Tx_Control__37">Tx_Control__1</entry>
	<entry key="Tx_Control__38">Tx_Control__1</entry>
	<entry key="Tx_Control__39">Tx_Control__1</entry>
	<entry key="Tx_Control__40">Tx_Control__1</entry>
	<entry key="Tx_Control__41">Tx_Control__1</entry>
	<entry key="Tx_Control__42">Tx_Control__1</entry>
	<entry key="Tx_Control__43">Tx_Control__1</entry>
	<entry key="Tx_Control__44">Tx_Control__1</entry>
	<entry key="Tx_Control__45">Tx_Control__1</entry>
	<entry key="Tx_Control__46">Tx_Control__1</entry>
	<entry key="Tx_Control__47">Tx_Control__1</entry>
	<entry key="Tx_Control__48">Tx_Control__1</entry>
	<entry key="Tx_Control__49">Tx_Control__1</entry>
	<entry key="Tx_Control__50">Tx_Control__1</entry>
	<entry key="Tx_Control__51">Tx_Control__1</entry>
	<entry key="Tx_Control__52">Tx_Control__1</entry>
	<entry key="Tx_Control__53">Tx_Control__1</entry>
	<entry key="Tx_Control__54">Tx_Control__1</entry>
	<entry key="Tx_Control__55">Tx_Control__1</entry>
	<entry key="Tx_Control__56">Tx_Control__1</entry>
	<entry key="Tx_Control__57">Tx_Control__1</entry>
	<entry key="Tx_Control__58">Tx_Control__1</entry>
	<entry key="Tx_Control__59">Tx_Control__1</entry>
	<entry key="Tx_Control__60">Tx_Control__1</entry>
	<entry key="Tx_Control__61">Tx_Control__1</entry>
	<entry key="Tx_Control__62">Tx_Control__1</entry>
	<entry key="Tx_Control__63">Tx_Control__1</entry>
	<entry key="Tx_Servo__2">Tx_Servo__1</entry>
	<entry key="Tx_Servo__3">Tx_Servo__1</entry>
	<entry key="Tx_Servo__4">Tx_Servo__1</entry>
	<entry key="Tx_Servo__5">Tx_Servo__1</entry>
	<entry key="Tx_Servo__6">Tx_Servo__1</entry>
	<entry key="Tx_Servo__7">Tx_Servo__1</entry>
	<entry key="Tx_Servo__8">Tx_Servo__1</entry>
	<entry key="Tx_Servo__9">Tx_Servo__1</entry>
	<entry key="Tx_Servo__10">Tx_Servo__1</entry>
	<entry key="Tx_Servo__11">Tx_Servo__1</entry>
	<entry key="Tx_Servo__12">Tx_Servo__1</entry>
	<entry key="Tx_Servo__13">Tx_Servo__1</entry>
	<entry key="Tx_Servo__14">Tx_Servo__1</entry>
	<entry key="Tx_Servo__15">Tx_Servo__1</entry>
	<entry key="Tx_Servo__16">Tx_Servo__1</entry>
	<entry key="Tx_Servo__17">Tx_Servo__1</entry>
	<entry key="Tx_Servo__18">Tx_Servo__1</entry>
	<entry key="Tx_Servo__19">Tx_Servo__1</entry>
	<entry key="Tx_Servo__20">Tx_Servo__1</entry>
	<entry key="Tx_Servo__21">Tx_Servo__1</entry>
	<entry key="Tx_Servo__22">Tx_Servo__1</entry>
	<entry key="Tx_Servo__23">Tx_Servo__1</entry>
	<entry key="Tx_Servo__24">Tx_Servo__1</entry>
	<entry key="Tx_Servo__25">Tx_Servo__1</entry>
	<entry key="Tx_Servo__26">Tx_Servo__1</entry>
	<entry key="Tx_Servo__27">Tx_Servo__1</entry>
	<entry key="Tx_Servo__28">Tx_Servo__1</entry>
	<entry key="Tx_Servo__29">Tx_Servo__1</entry>
	<entry key="Tx_Servo__30">Tx_Servo__1</entry>
	<entry key="Tx_Servo__31">Tx_Servo__1</entry>
	<entry key="Tx_Servo__32">Tx_Servo__1</entry>
	<entry key="Tx_Servo__33">Tx_Servo__1</entry>
	<entry key="Tx_Servo__34">Tx_Servo__1</entry>
	<entry key="Tx_Servo__35">Tx_Servo__1</entry>
	<entry key="Tx_Servo__36">Tx_Servo__1</entry>
	<entry key="Tx_Servo__37">Tx_Servo__1</entry>
	<entry key="Tx_Servo__38">Tx_Servo__1</entry>
	<entry key="Tx_Servo__39">Tx_Servo__1</entry>
	<entry key="Tx_Servo__40">Tx_Servo__1</entry>
	<entry key="Tx_Servo__41">Tx_Servo__1</entry>
	<entry key="Tx_Servo__42">Tx_Servo__1</entry>
	<entry key="Tx_Servo__43">Tx_Servo__1</entry>
	<entry key="Tx_Servo__44">Tx_Servo__1</entry>
	<entry key="Tx_Servo__45">Tx_Servo__1</entry>
	<entry key="Tx_Servo__46">Tx_Servo__1</entry>
	<entry key="Tx_Servo__47">Tx_Servo__1</entry>
	<entry key="Tx_Servo__48">Tx_Servo__1</entry>
	<entry key="Tx_Servo__49">Tx_Servo__1</entry>
	<entry key="Tx_Servo__50">Tx_Servo__1</entry>
	<entry key="Tx_Servo__51">Tx_Servo__1</entry>
	<entry key="Tx_Servo__52">Tx_Servo__1</entry>
	<entry key="Tx_Servo__53">Tx_Servo__1</entry>
	<entry key="Tx_Servo__54">Tx_Servo__1</entry>
	<entry key="Tx_Servo__55">Tx_Servo__1</entry>
	<entry key="Tx_Servo__56">Tx_Servo__1</entry>
	<entry key="Tx_Servo__57">Tx_Servo__1</entry>
	<entry key="Tx_Servo__58">Tx_Servo__1</entry>
	<entry key="Tx_Servo__59">Tx_Servo__1</entry>
	<entry key="Tx_Servo__60">Tx_Servo__1</entry>
	<entry key="Tx_Servo__61">Tx_Servo__1</entry>
	<entry key="Tx_Servo__62">Tx_Servo__1</entry>
	<entry key="Tx_Servo__63">Tx_Servo__1</entry>
	<entry key="New Function_2">New Function_1</entry>
	<entry key="New Function_3">New Function_1</entry>
	<entry key="New Function_4">New Function_1</entry>
	<entry key="New Function_5">New Function_1</entry>
	<entry key="New Function_6">New Function_1</entry>
	<entry key="New Function_7">New Function_1</entry>
	<entry key="New Function_8">New Function_1</entry>
	<entry key="New Function_9">New Function_1</entry>
	<entry key="New Function_10">New Function_1</entry>
	<entry key="New Function_11">New Function_1</entry>
	<entry key="New Function_12">New Function_1</entry>
	<entry key="New Function_13">New Function_1</entry>
	<entry key="New Function_14">New Function_1</entry>
	<entry key="New Function_15">New Function_1</entry>
	<entry key="New Function_16">New Function_1</entry>
	<entry key="New Function_17">New Function_1</entry>
	<entry key="New Function_18">New Function_1</entry>
	<entry key="New Function_19">New Function_1</entry>
	<entry key="New Function_20">New Function_1</entry>
	<entry key="New Function_21">New Function_1</entry>
	<entry key="New Function_22">New Function_1</entry>
	<entry key="New Function_23">New Function_1</entry>
	<entry key="New Function_24">New Function_1</entry>
	<entry key="New Function_25">New Function_1</entry>
	<entry key="New Function_26">New Function_1</entry>
	<entry key="New Function_27">New Function_1</entry>
	<entry key="New Function_28">New Function_1</entry>
	<entry key="New Function_29">New Function_1</entry>
	<entry key="New Function_30">New Function_1</entry>
	<entry key="New Function_31">New Function_1</entry>
	<entry key="New Function_32">New Function_1</entry>
	<entry key="New Function_33">New Function_1</entry>
	<entry key="New Function_34">New Function_1</entry>
	<entry key="New Function_35">New Function_1</entry>
	<entry key="New Function_36">New Function_1</entry>
	<entry key="New Function_37">New Function_1</entry>
	<entry key="New Function_38">New Function_1</entry>
	<entry key="New Function_39">New Function_1</entry>
	<entry key="New Function_40">New Function_1</entry>
	<entry key="New Function_41">New Function_1</entry>
	<entry key="New Function_42">New Function_1</entry>
	<entry key="New Function_43">New Function_1</entry>
	<entry key="New Function_44">New Function_1</entry>
	<entry key="New Function_45">New Function_1</entry>
	<entry key="New Function_46">New Function_1</entry>
	<entry key="New Function_47">New Function_1</entry>
	<entry key="New Function_48">New Function_1</entry>
	<entry key="New Function_49">New Function_1</entry>
	<entry key="New Function_50">New Function_1</entry>
	<entry key="New Function_51">New Function_1</entry>
	<entry key="New Function_52">New Function_1</entry>
	<entry key="New Function_53">New Function_1</entry>
	<entry key="New Function_54">New Function_1</entry>
	<entry key="New Function_55">New Function_1</entry>
	<entry key="New Function_56">New Function_1</entry>
	<entry key="New Function_57">New Function_1</entry>
	<entry key="New Function_58">New Function_1</entry>
	<entry key="New Function_59">New Function_1</entry>
	<entry key="New Function_60">New Function_1</entry>
	<entry key="New Function_61">New Function_1</entry>
	<entry key="New Function_62">New Function_1</entry>
	<entry key="New Function_63">New Function_1</entry>
	
	<entry key="Tx_ControlID__2">Tx_ControlID__1</entry>
	<entry key="Tx_ControlID__3">Tx_ControlID__1</entry>
	<entry key="Tx_ControlID__4">Tx_ControlID__1</entry>
	<entry key="Tx_ControlID__5">Tx_ControlID__1</entry>
	<entry key="Tx_ControlID__6">Tx_ControlID__1</entry>
	<entry key="Tx_ControlID__7">Tx_ControlID__1</entry>
	<entry key="Tx_ControlID__8">Tx_ControlID__1</entry>
	<entry key="Tx_ControlID__9">Tx_ControlID__1</entry>
	<entry key="Tx_ControlID__10">Tx_ControlID__1</entry>
	<entry key="Tx_ControlID__11">Tx_ControlID__1</entry>
	<entry key="Tx_ControlID__12">Tx_ControlID__1</entry>
	<entry key="Tx_ControlID__13">Tx_ControlID__1</entry>
	<entry key="Tx_ControlID__14">Tx_ControlID__1</entry>
	<entry key="Tx_ControlID__15">Tx_ControlID__1</entry>
	<entry key="Tx_ControlID__16">Tx_ControlID__1</entry>
	<entry key="Tx_ControlID__17">Tx_ControlID__1</entry>
	<entry key="Tx_ControlID__18">Tx_ControlID__1</entry>
	<entry key="Tx_ControlID__19">Tx_ControlID__1</entry>
	<entry key="Tx_ControlID__20">Tx_ControlID__1</entry>
	<entry key="Tx_ControlID__21">Tx_ControlID__1</entry>
	<entry key="Tx_ControlID__22">Tx_ControlID__1</entry>
	<entry key="Tx_ControlID__23">Tx_ControlID__1</entry>
	<entry key="Tx_ControlID__24">Tx_ControlID__1</entry>
	<entry key="Tx_ControlID__25">Tx_ControlID__1</entry>
	<entry key="Tx_ControlID__26">Tx_ControlID__1</entry>
	<entry key="Tx_ControlID__27">Tx_ControlID__1</entry>
	<entry key="Tx_ControlID__28">Tx_ControlID__1</entry>
	<entry key="Tx_ControlID__29">Tx_ControlID__1</entry>
	<entry key="Tx_ControlID__30">Tx_ControlID__1</entry>
	<entry key="Tx_ControlID__31">Tx_ControlID__1</entry>
	<entry key="Tx_ControlID__32">Tx_ControlID__1</entry>
	<entry key="Tx_ControlID__33">Tx_ControlID__1</entry>
	<entry key="Tx_ControlID__34">Tx_ControlID__1</entry>
	<entry key="Tx_ControlID__35">Tx_ControlID__1</entry>
	<entry key="Tx_ControlID__36">Tx_ControlID__1</entry>
	<entry key="Tx_ControlID__37">Tx_ControlID__1</entry>
	<entry key="Tx_ControlID__38">Tx_ControlID__1</entry>
	<entry key="Tx_ControlID__39">Tx_ControlID__1</entry>
	<entry key="Tx_ControlID__40">Tx_ControlID__1</entry>
	<entry key="Tx_ControlID__41">Tx_ControlID__1</entry>
	<entry key="Tx_ControlID__42">Tx_ControlID__1</entry>
	<entry key="Tx_ControlID__43">Tx_ControlID__1</entry>
	<entry key="Tx_ControlID__44">Tx_ControlID__1</entry>
	<entry key="Tx_ControlID__45">Tx_ControlID__1</entry>
	<entry key="Tx_ControlID__46">Tx_ControlID__1</entry>
	<entry key="Tx_ControlID__47">Tx_ControlID__1</entry>
	<entry key="Tx_ControlID__48">Tx_ControlID__1</entry>
	<entry key="Tx_ControlID__49">Tx_ControlID__1</entry>
	<entry key="Tx_ControlID__50">Tx_ControlID__1</entry>
	<entry key="Tx_ControlID__51">Tx_ControlID__1</entry>
	<entry key="Tx_ControlID__52">Tx_ControlID__1</entry>
	<entry key="Tx_ControlID__53">Tx_ControlID__1</entry>
	<entry key="Tx_ControlID__54">Tx_ControlID__1</entry>
	<entry key="Tx_ControlID__55">Tx_ControlID__1</entry>
	<entry key="Tx_ControlID__56">Tx_ControlID__1</entry>
	<entry key="Tx_ControlID__57">Tx_ControlID__1</entry>
	<entry key="Tx_ControlID__58">Tx_ControlID__1</entry>
	<entry key="Tx_ControlID__59">Tx_ControlID__1</entry>
	<entry key="Tx_ControlID__60">Tx_ControlID__1</entry>
	<entry key="Tx_ControlID__61">Tx_ControlID__1</entry>
	<entry key="Tx_ControlID__62">Tx_ControlID__1</entry>
	<entry key="Tx_ControlID__63">Tx_ControlID__1</entry>

	<entry key="Rx_GyroInt1">Rx_GyroInt0</entry>
	<entry key="Rx_GyroInt2">Rx_GyroInt0</entry>
	<entry key="Rx_GyroExt0">Rx_GyroInt0</entry>
	<entry key="Rx_GyroExt1">Rx_GyroInt0</entry>
</properties>
